Workbook

Sheet README
A1: FinTrack Stock Tracker — README
A3: HOW TO USE THIS WORKBOOK
A4: 1. Enter your holdings on the relevant market sheet (Roth IRA, US Stocks, ETFs, etc.)
A5: 2. Blue cells are inputs — fill in Ticker, Company, Shares, Buy Price, and Current Price
A6: 3. Black cells are formulas — they calculate automatically, do not edit them
A7: 4. Update Current Price regularly (use the Price Log sheet to track updates)
A8: 5. The Summary sheet pulls totals from all market sheets automatically
A10: COLOR GUIDE
A11: Blue text = hardcoded input (you enter this)
A12: Black text = calculated formula (auto)
A13: Green text = cross-sheet reference
A15: MARKET SHEETS
... A24: Or manually update Current Price on each card in the dashboard — both stay in sync.

Sheet Summary
A1: FinTrack — Portfolio Summary
A2: Auto-calculated from all market sheets — update Current Price on each sheet to refresh
A3: Market | B3: Total Cost ($) | C3: Current Value ($) | D3: Gain / Loss ($) | E3: Gain / Loss (%) | F3: # Holdings | G3: % of Portfolio
A4: Roth IRA | B4: ='Roth IRA'!F24 | C4: ='Roth IRA'!G24 | D4: ='Roth IRA'!H24 | E4: ='Roth IRA'!I24 | F4: =COUNTA('Roth IRA'!A4:A23) | G4: =IF(SUM(C4:C8)=0,"",C4/SUM(C4:C8))
A5: US Stocks | B5: ='US Stocks'!F24 | C5: ='US Stocks'!G24 | D5: ='US Stocks'!H24 | E5: ='US Stocks'!I24 | F5: =COUNTA('US Stocks'!A4:A23) | G5: =IF(SUM(C4:C8)=0,"",C5/SUM(C4:C8))
A6: ETFs | B6: ='ETFs'!F24 | C6: ='ETFs'!G24 | D6: ='ETFs'!H24 | E6: ='ETFs'!I24 | F6: =COUNTA('ETFs'!A4:A23) | G6: =IF(SUM(C4:C8)=0,"",C6/SUM(C4:C8))
A7: International | B7: ='International'!F24 | C7: ='International'!G24 | D7: ='International'!H24 | E7: ='International'!I24 | F7: =COUNTA('International'!A4:A23) | G7: =IF(SUM(C4:C8)=0,"",C7/SUM(C4:C8))
A8: Crypto | B8: ='Crypto'!F24 | C8: ='Crypto'!G24 | D8: ='Crypto'!H24 | E8: ='Crypto'!I24 | F8: =COUNTA('Crypto'!A4:A23) | G8: =IF(SUM(C4:C8)=0,"",C8/SUM(C4:C8))
A9: GRAND TOTAL | B9: =SUM(B4:B8) | C9: =SUM(C4:C8) | D9: =SUM(D4:D8) | E9: =IF(B9=0,"",D9/B9)

Sheet Roth IRA
A1: 📊 Roth IRA — Stock & ETF Tracker
A2: Blue = hardcoded inputs (edit these) | Black = formulas (auto-calculated) | Green = cross-sheet links
A3: Ticker | B3: Company / Name | C3: Shares | D3: Buy Price ($) | E3: Current Price ($) | F3: Total Cost ($) | G3: Current Value ($) | H3: Gain / Loss ($) | I3: Gain / Loss (%) | J3: Notes
A4: SCHB | B4: Schwab US Broad Market ETF | C4: 12 | D4: 56 | E4: 56 | F4: =IF(C4="","",C4*D4) | G4: =IF(C4="","",C4*E4) | H4: =IF(C4="","",G4-F4) | I4: =IF(OR(C4="",F4=0),"",H4/F4)
A5: SCHF | B5: Schwab International Equity ETF | C5: 8 | D5: 35.5 | E5: 35.5 | F5: =IF(C5="","",C5*D5) | G5: =IF(C5="","",C5*E5) | H5: =IF(C5="","",G5-F5) | I5: =IF(OR(C5="",F5=0),"",H5/F5)
A6: CHPY | B6: YieldMax Semiconductor Portfolio | C6: 12 | D6: 56 | E6: 56 | F6: =IF(C6="","",C6*D6) | G6: =IF(C6="","",C6*E6) | H6: =IF(C6="","",G6-F6) | I6: =IF(OR(C6="",F6=0),"",H6/F6)
A24: TOTALS | F24: =SUMIF(F4:F23,"<>",F4:F23) | G24: =SUMIF(G4:G23,"<>",G4:G23) | H24: =SUMIF(H4:H23,"<>",H4:H23) | I24: =IF(F24=0,"",H24/F24)

Sheet US Stocks
A1: 📊 US Stocks — Stock & ETF Tracker
A2: Blue = hardcoded inputs (edit these) | Black = formulas (auto-calculated) | Green = cross-sheet links
A3: Ticker | B3: Company / Name | C3: Shares | D3: Buy Price ($) | E3: Current Price ($) | F3: Total Cost ($) | G3: Current Value ($) | H3: Gain / Loss ($) | I3: Gain / Loss (%) | J3: Notes
A24: TOTALS | F24: =SUMIF(F4:F23,"<>",F4:F23) | G24: =SUMIF(G4:G23,"<>",G4:G23) | H24: =SUMIF(H4:H23,"<>",H4:H23) | I24: =IF(F24=0,"",H24/F24)

Sheet ETFs
A1: 📊 ETFs — Stock & ETF Tracker
A2: Blue = hardcoded inputs (edit these) | Black = formulas (auto-calculated) | Green = cross-sheet links
A3: Ticker | B3: Company / Name | C3: Shares | D3: Buy Price ($) | E3: Current Price ($) | F3: Total Cost ($) | G3: Current Value ($) | H3: Gain / Loss ($) | I3: Gain / Loss (%) | J3: Notes
A24: TOTALS | F24: =SUMIF(F4:F23,"<>",F4:F23) | G24: =SUMIF(G4:G23,"<>",G4:G23) | H24: =SUMIF(H4:H23,"<>",H4:H23) | I24: =IF(F24=0,"",H24/F24)

Sheet International
A1: 📊 International — Stock & ETF Tracker
A2: Blue = hardcoded inputs (edit these) | Black = formulas (auto-calculated) | Green = cross-sheet links
A3: Ticker | B3: Company / Name | C3: Shares | D3: Buy Price ($) | E3: Current Price ($) | F3: Total Cost ($) | G3: Current Value ($) | H3: Gain / Loss ($) | I3: Gain / Loss (%) | J3: Notes
A24: TOTALS | F24: =SUMIF(F4:F23,"<>",F4:F23) | G24: =SUMIF(G4:G23,"<>",G4:G23) | H24: =SUMIF(H4:H23,"<>",H4:H23) | I24: =IF(F24=0,"",H24/F24)

Sheet Crypto
A1: 📊 Crypto — Stock & ETF Tracker
A2: Blue = hardcoded inputs (edit these) | Black = formulas (auto-calculated) | Green = cross-sheet links
A3: Ticker | B3: Company / Name | C3: Shares | D3: Buy Price ($) | E3: Current Price ($) | F3: Total Cost ($) | G3: Current Value ($) | H3: Gain / Loss ($) | I3: Gain / Loss (%) | J3: Notes
A24: TOTALS | F24: =SUMIF(F4:F23,"<>",F4:F23) | G24: =SUMIF(G4:G23,"<>",G4:G23) | H24: =SUMIF(H4:H23,"<>",H4:H23) | I24: =IF(F24=0,"",H24/F24)

Sheet Price Log
A1: 📅 Price Update Log — Track every price entry here
A2: Enter date, market sheet, ticker, and price. This creates a manual audit trail.
A3: Date | B3: Market Sheet | C3: Ticker | D3: Price ($) | E3: Shares | F3: Notes
